.gitignore
Dockerfile
Makefile
README.md
main.py
main_slurm.py
requirements.txt
setup.py
idlem/__init__.py
idlem/arg_parser.py
idlem/run.py
idlem/utils.py
idlem.egg-info/PKG-INFO
idlem.egg-info/SOURCES.txt
idlem.egg-info/dependency_links.txt
idlem.egg-info/entry_points.txt
idlem.egg-info/requires.txt
idlem.egg-info/top_level.txt
idlem/configs/conf.txt
idlem/configs/config.yaml
idlem/configs/config_pip.yaml
idlem/configs/config_slurm.yaml
idlem/configs/miner/eth.yaml
idlem/configs/miner/gminer_eth.yaml
idlem/configs/miner/trex_eth.yaml
idlem/configs/scheduler/full.yaml
idlem/configs/scheduler/night.yaml
tests/test_utils.py