Metadata-Version: 2.1
Name: idlem
Version: 0.0.6
Summary: idle-m
Home-page: UNKNOWN
Author: ...
Author-email: some@mail.com
License: MIT License
Platform: UNKNOWN
Classifier: Programming Language :: Python :: 3.6
Classifier: Programming Language :: Python :: 3.7
Requires-Python: >=3, <4
